[{"timestamp":"2023-07-14T00:52:05.647Z","count":0,"uniques":0},{"timestamp":"2023-07-15T00:49:45.839Z","count":0,"uniques":0},{"timestamp":"2023-07-16T00:57:04.459Z","count":0,"uniques":0},{"timestamp":"2023-07-17T00:54:56.325Z","count":0,"uniques":0},{"timestamp":"2023-07-18T01:08:55.244Z","count":0,"uniques":0},{"timestamp":"2023-07-19T01:19:28.041Z","count":0,"uniques":0},{"timestamp":"2023-07-20T00:44:08.113Z","count":0,"uniques":0},{"timestamp":"2023-07-21T00:44:00.442Z","count":0,"uniques":0}]
